<?xml version="1.0" encoding="UTF-8"?>
<!DOCTYPE plist PUBLIC "-//Apple//DTD PLIST 1.0//EN" "http://www.apple.com/DTDs/PropertyList-1.0.dtd"/>

<plist version="1.0">
    <dict>
        <key>ROOT</key>
        <array>
            <dict>
                <key>id</key>
                <string>5411</string>
                <key>className</key>
                <string>PTModelObjectAssetTeleport</string>
                <key>Name</key>
                <dict>
                    <key>value</key>
                    <string>Portal</string>
                </dict>
                <key>Position</key>
                <dict>
                    <key>value</key>
                    <string>{1090.000,160.000}</string>
                </dict>
                <key>Scale</key>
                <dict>
                    <key>value</key>
                    <string>{1.000,1.000}</string>
                </dict>
                <key>Hidden</key>
                <dict>
                    <key>visible</key>
                    <string>0</string>
                </dict>
                <key>Locked</key>
                <dict>
                    <key>visible</key>
                    <string>0</string>
                </dict>
                <key>Opacity</key>
                <dict>
                    <key>visible</key>
                    <string>0</string>
                </dict>
                <key>zDepth</key>
                <string>503</string>
            </dict>
            <dict>
                <key>id</key>
                <string>5518</string>
                <key>className</key>
                <string>PTModelObjectAssetTeleport</string>
                <key>Name</key>
                <dict>
                    <key>value</key>
                    <string>Portal 2</string>
                </dict>
                <key>Position</key>
                <dict>
                    <key>value</key>
                    <string>{1660.000,260.000}</string>
                </dict>
                <key>Scale</key>
                <dict>
                    <key>value</key>
                    <string>{1.000,1.000}</string>
                </dict>
                <key>Hidden</key>
                <dict>
                    <key>visible</key>
                    <string>0</string>
                </dict>
                <key>Locked</key>
                <dict>
                    <key>visible</key>
                    <string>0</string>
                </dict>
                <key>Opacity</key>
                <dict>
                    <key>visible</key>
                    <string>0</string>
                </dict>
                <key>Group ID</key>
                <dict>
                    <key>value</key>
                    <string>1.000000</string>
                </dict>
                <key>zDepth</key>
                <string>504</string>
            </dict>
            <dict>
                <key>id</key>
                <string>5530</string>
                <key>className</key>
                <string>PTModelObjectAssetTeleport</string>
                <key>Name</key>
                <dict>
                    <key>value</key>
                    <string>Portal 3</string>
                </dict>
                <key>Position</key>
                <dict>
                    <key>value</key>
                    <string>{1450.000,260.000}</string>
                </dict>
                <key>Scale</key>
                <dict>
                    <key>value</key>
                    <string>{1.000,1.000}</string>
                </dict>
                <key>Hidden</key>
                <dict>
                    <key>visible</key>
                    <string>0</string>
                </dict>
                <key>Locked</key>
                <dict>
                    <key>visible</key>
                    <string>0</string>
                </dict>
                <key>Opacity</key>
                <dict>
                    <key>visible</key>
                    <string>0</string>
                </dict>
                <key>zDepth</key>
                <string>505</string>
            </dict>
            <dict>
                <key>id</key>
                <string>5536</string>
                <key>className</key>
                <string>PTModelObjectAssetTeleport</string>
                <key>Name</key>
                <dict>
                    <key>value</key>
                    <string>Portal 4</string>
                </dict>
                <key>Position</key>
                <dict>
                    <key>value</key>
                    <string>{1760.000,570.000}</string>
                </dict>
                <key>Scale</key>
                <dict>
                    <key>value</key>
                    <string>{1.000,1.000}</string>
                </dict>
                <key>Hidden</key>
                <dict>
                    <key>visible</key>
                    <string>0</string>
                </dict>
                <key>Locked</key>
                <dict>
                    <key>visible</key>
                    <string>0</string>
                </dict>
                <key>Opacity</key>
                <dict>
                    <key>visible</key>
                    <string>0</string>
                </dict>
                <key>Group ID</key>
                <dict>
                    <key>value</key>
                    <string>1.000000</string>
                </dict>
                <key>zDepth</key>
                <string>506</string>
            </dict>
        </array>
    </dict>
</plist>
